<properties>
	<property id="totalDistance" type="number">0</property>
	<property id="maxDistance" type="number">0</property>

	<property id="totalDistanceLastYear" type="number">0</property>
	<property id="totalDistanceYear" type="number">0</property>
	
	<property id="totalDistanceLastMonth" type="number">0</property>		
	<property id="totalDistanceMonth" type="number">0</property>		
		
	<property id="totalDistanceLastWeek" type="number">0</property>		
	<property id="totalDistanceWeek" type="number">0</property>		

	<property id="totalDistanceLastRide" type="number">0</property>		
	<property id="totalDistanceRide" type="number">0</property>		
	
	<property id="showColors" type="boolean">true</property>		
	<property id="showValues" type="boolean">true</property>		
	<property id="showColorsSmallField" type="boolean">true</property>		
	<property id="showValuesSmallField" type="boolean">false</property>		

	<property id="triggerFrontTyre" type="string">Front</property>		
	<property id="totalDistanceFrontTyre" type="number">0</property>		
	<property id="maxDistanceFrontTyre" type="number">9000</property>		
	<property id="triggerBackTyre" type="string">Back</property>		
	<property id="totalDistanceBackTyre" type="number">0</property>		
	<property id="maxDistanceBackTyre" type="number">3000</property>		

	<property id="showFocusSmallField" type="number">0</property>			
	<property id="showFields" type="string">ORMWYFB</property>		
</properties>